{
  "workflow": "AI-Powered Sustainable Fashion Rental Marketplace",
  "components": {
    "userInterface": {
      "features": [
        "User Registration and Profile Management",
        "Browse and Search Catalog",
        "Filters (Size, Style, Occasion, Sustainability Score)",
        "Item Details with Rental Pricing",
        "Rental Booking and Payment",
        "Order Tracking and History",
        "Return Management",
        "User Reviews and Ratings"
      ]
    },
    "catalogManagement": {
      "inventory": {
        "itemDetails": [
          "Product Name",
          "Description",
          "Sizes Available",
          "Material and Sustainability Info",
          "Rental Price Base",
          "Images",
          "Quantity Available"
        ],
        "realTimeInventoryTracking": true,
        "itemStatus": ["Available", "Rented", "Under Maintenance", "Returned", "Lost"]
      },
      "dynamicPricing": {
        "factors": [
          "Demand-based adjustments",
          "Seasonality",
          "Item condition and usage history",
          "Sustainability score incentives",
          "Promotions and Discounts"
        ],
        "AIModel": {
          "inputFeatures": [
            "Current Demand Level",
            "Rental Frequency",
            "Return Rates",
            "Time on Marketplace",
            "Customer Ratings",
            "Seasonal Trends"
          ],
          "output": "Optimized Rental Price"
        }
      }
    },
    "rentalManagement": {
      "booking": {
        "availabilityCheck": true,
        "rentalPeriodOptions": ["1 day", "3 days", "1 week", "2 weeks"],
        "paymentProcessing": ["Credit Card", "Digital Wallets", "Promotional Codes"]
      },
      "returnHandling": {
        "returnScheduling": true,
        "conditionAssessment": {
          "manualInspection": true,
          "AIImageRecognition": {
            "damageDetection": true,
            "wearAndTearAssessment": true
          }
        },
        "restocking": true,
        "penalties": {
          "lateReturnFee": true,
          "damageFee": true
        }
      }
    },
    "aiSystems": {
      "pricingModel": {
        "type": "Regression & Time Series Analysis",
        "trainingData": ["Historical Rental Data", "Market Trends", "Customer Feedback"],
        "updateFrequency": "Daily"
      },
      "inventoryForecasting": {
        "type": "Predictive Analytics",
        "goal": "Optimize inventory levels based on expected demand",
        "inputData": ["Rental History", "Search Trends", "Seasonality"],
        "output": "Inventory Replenishment Recommendations"
      },
      "itemConditionAssessment": {
        "type": "Computer Vision",
        "features": ["Damage Detection", "Wear Level Estimation"],
        "integrationPoint": "Return Handling Process"
      }
    },
    "backendServices": {
      "database": {
        "userProfiles": true,
        "catalogItems": true,
        "rentalTransactions": true,
        "payments": true,
        "returns": true,
        "reviews": true
      },
      "api": {
        "catalogAPI": "Handles product listing, search, filter, and details",
        "rentalAPI": "Booking, availability, payment processing",
        "returnAPI": "Scheduling, condition reports, penalties",
        "pricingAPI": "Dynamic pricing calculations",
        "aiModelAPI": "Serve AI predictions and assessments"
      },
      "notifications": [
        "Rental Confirmation",
        "Return Reminders",
        "Pricing Updates",
        "Promotional Offers"
      ]
    },
    "analyticsAndReporting": {
      "metricsTracked": [
        "Rental Frequency",
        "Revenue per Item",
        "Return Rates and Condition Scores",
        "Customer Satisfaction",
        "Pricing Effectiveness"
      ],
      "feedbackLoop": {
        "aiModelTrainingData": [
          "Rental and Return Data",
          "User Reviews",
          "Pricing Outcomes"
        ]
      }
    },
    "sustainabilityFeatures": {
      "sustainabilityScore": {
        "criteria": [
          "Material Source",
          "Production Impact",
          "Rental Frequency",
          "Lifecycle Carbon Footprint"
        ],
        "incentives": [
          "Discounts for High Sustainability Score Items",
          "Promotional Badges"
        ]
      },
      "education": {
        "content": [
          "Sustainable Fashion Tips",
          "Benefits of Rental over Buying",
          "Environmental Impact Data"
        ]
      }
    }
  }
}